infisical_sdk/__init__.py
infisical_sdk/api_types.py
infisical_sdk/client.py
infisical_sdk/infisical_requests.py
infisical_sdk/resources/__init__.py
infisical_sdk/resources/auth.py
infisical_sdk/resources/dynamic_secrets.py
infisical_sdk/resources/folders.py
infisical_sdk/resources/kms.py
infisical_sdk/resources/secrets.py
infisical_sdk/resources/auth_methods/__init__.py
infisical_sdk/resources/auth_methods/aws_auth.py
infisical_sdk/resources/auth_methods/oidc_auth.py
infisical_sdk/resources/auth_methods/token_auth.py
infisical_sdk/resources/auth_methods/universal_auth.py
infisical_sdk/util/__init__.py
infisical_sdk/util/secrets_cache.py
infisicalsdk-1.0.15.dist-info/licenses/LICENSE
infisicalsdk-1.0.15.dist-info/METADATA
infisicalsdk-1.0.15.dist-info/WHEEL
infisicalsdk-1.0.15.dist-info/top_level.txt
infisicalsdk-1.0.15.dist-info/RECORD
