Metadata-Version: 2.4
Name: infisicalsdk
Version: 1.0.15
Summary: Official Infisical SDK for Python (Latest)
Home-page: https://github.com/Infisical/python-sdk-official
Author: Infisical
Author-email: support@infisical.com
Keywords: Infisical,Infisical API,Infisical SDK,SDK,Secrets Management
License-File: LICENSE
Requires-Dist: python-dateutil
Requires-Dist: aenum
Requires-Dist: requests~=2.32
Requires-Dist: boto3~=1.35
Requires-Dist: botocore~=1.35
Dynamic: author
Dynamic: author-email
Dynamic: description
Dynamic: description-content-type
Dynamic: home-page
Dynamic: keywords
Dynamic: license-file
Dynamic: requires-dist
Dynamic: summary
